kafkaaggregator/__init__.py
kafkaaggregator/aggregator.py
kafkaaggregator/app.py
kafkaaggregator/cli.py
kafkaaggregator/config.py
kafkaaggregator/example.py
kafkaaggregator/fields.py
kafkaaggregator/generator.py
kafkaaggregator/models.py
kafkaaggregator/operations.py
kafkaaggregator/topics.py
kafkaaggregator/templates/agent.j2
kafka_aggregator-0.2.0.dist-info/METADATA
kafka_aggregator-0.2.0.dist-info/WHEEL
kafka_aggregator-0.2.0.dist-info/entry_points.txt
kafka_aggregator-0.2.0.dist-info/top_level.txt
kafka_aggregator-0.2.0.dist-info/RECORD
