Metadata-Version: 2.1
Name: kafka-aggregator
Version: 0.2.0
Summary: A Kafka aggregator based on the Faust stream processing library.
Home-page: https://github.com/lsst-sqre/kafka-aggregator
Author: Association of Universities for Research in Astronomy, Inc. (AURA)
Author-email: sqre-admin@lists.lsst.org
License: UNKNOWN
Project-URL: Change log, https://github.com/lsst-sqre/kafka-aggregator/master/blob/CHANGELOG.rst
Project-URL: Source code, https://github.com/lsst-sqre/kafka-aggregator
Project-URL: Issue tracker, https://github.com/lsst-sqre/kafka-aggregator/issues
Keywords: lsst
Platform: UNKNOWN
Classifier: Development Status :: 4 - Beta
Classifier: License :: OSI Approved :: MIT License
Classifier: Programming Language :: Python
Classifier: Programming Language :: Python :: 3
Classifier: Programming Language :: Python :: 3.7
Classifier: Natural Language :: English
Classifier: Operating System :: POSIX
Requires-Python: >=3.7
